leya/__init__.py
leya/cli.py
leya/core.py
leya/repo_states.py
leya/processors/__init__.py
leya/processors/file_processor.py
leya/processors/repo_processor.py
leya/services/__init__.py
leya/services/openai.py
leya/services/pincecone.py
leya/utils/__init__.py
leya/utils/condense_file.py
leya/utils/embedPrompt.py
leya/utils/format_text.py
leya/utils/set_enivronment_variables.py
leya-0.1.5.dist-info/License.txt
leya-0.1.5.dist-info/METADATA
leya-0.1.5.dist-info/WHEEL
leya-0.1.5.dist-info/entry_points.txt
leya-0.1.5.dist-info/top_level.txt
leya-0.1.5.dist-info/RECORD
