Metadata-Version: 2.1
Name: leya
Version: 0.1.5
Summary: A coding assistant to help with repository management and code queries.
Author: Pranav Iyer
Author-email: pn2229@nyu.edu
License-File: License.txt
Requires-Dist: annotated-types (==0.6.0)
Requires-Dist: anyio (==4.3.0)
Requires-Dist: astunparse (==1.6.3)
Requires-Dist: blinker (==1.7.0)
Requires-Dist: cachelib (==0.12.0)
Requires-Dist: charset-normalizer (==3.3.2)
Requires-Dist: click (==8.1.7)
Requires-Dist: colorama (==0.4.6)
Requires-Dist: fsspec (==2024.3.1)
Requires-Dist: future (==0.18.3)
Requires-Dist: gitdb (==4.0.11)
Requires-Dist: GitPython (==3.1.43)
Requires-Dist: h11 (==0.14.0)
Requires-Dist: httpcore (==1.0.5)
Requires-Dist: httpx (==0.27.0)
Requires-Dist: idna (==3.6)
Requires-Dist: iniconfig (==2.0.0)
Requires-Dist: itsdangerous (==2.1.2)
Requires-Dist: markdown-it-py (==3.0.0)
Requires-Dist: MarkupSafe (==2.1.5)
Requires-Dist: mdurl (==0.1.2)
Requires-Dist: mpmath (==1.3.0)
Requires-Dist: msgspec (==0.18.6)
Requires-Dist: numpy (==1.26.4)
Requires-Dist: packaging (==24.0)
Requires-Dist: pinecone-client (==3.2.2)
Requires-Dist: pluggy (==1.5.0)
Requires-Dist: pydantic (==2.6.4)
Requires-Dist: pydantic-core (==2.16.3)
Requires-Dist: Pygments (==2.17.2)
Requires-Dist: pytest (==8.1.1)
Requires-Dist: python-dotenv (==1.0.1)
Requires-Dist: PyYAML (==6.0.1)
Requires-Dist: regex (==2024.4.16)
Requires-Dist: requests (==2.31.0)
Requires-Dist: rich (==13.7.1)
Requires-Dist: safetensors (==0.4.3)
Requires-Dist: scipy (==1.13.0)
Requires-Dist: six (==1.16.0)
Requires-Dist: smart-open (==7.0.4)
Requires-Dist: smmap (==5.0.1)
Requires-Dist: sniffio (==1.3.1)
Requires-Dist: soupsieve (==2.5)
Requires-Dist: sympy (==1.12)
Requires-Dist: tokenizers (==0.19.1)
Requires-Dist: torch (==2.2.2)
Requires-Dist: tqdm (==4.66.2)
Requires-Dist: typing-extensions (==4.11.0)
Requires-Dist: urllib3 (==2.2.1)
Requires-Dist: Werkzeug (==3.0.2)
Requires-Dist: wrapt (==1.16.0)
Requires-Dist: zipp (==3.18.1)
